django_cognito/__init__.py
django_cognito/local_settings.py
django_cognito/settings.py
django_cognito/tests.py
django_cognito/urls.py
django_cognito/authentication/__init__.py
django_cognito/authentication/apps.py
django_cognito/authentication/urls.py
django_cognito/authentication/utils.py
django_cognito/authentication/views.py
django_cognito/authentication/cognito/__init__.py
django_cognito/authentication/cognito/actions.py
django_cognito/authentication/cognito/base.py
django_cognito/authentication/cognito/constants.py
django_cognito/authentication/cognito/helpers.py
django_cognito/authentication/middleware/__init__.py
django_cognito/authentication/middleware/cognito_django_authentication.py
django_cognito/authentication/middleware/cognito_django_middleware.py
django_cognito/authentication/middleware/cognito_rest_authentication.py
django_cognito/authentication/middleware/helpers.py
django_cognito-1.2.0.dist-info/LICENSE
django_cognito-1.2.0.dist-info/METADATA
django_cognito-1.2.0.dist-info/WHEEL
django_cognito-1.2.0.dist-info/top_level.txt
django_cognito-1.2.0.dist-info/RECORD
