Metadata-Version: 2.1
Name: django-cognito
Version: 1.2.0
Summary: Library for allowing the use of AWS Cognito security in Django projects
Home-page: https://github.com/Olorin92/django_cognito
Author: Alex Plant
Author-email: alex.c.plant@gmail.com
License: UNKNOWN
Platform: UNKNOWN
Requires-Dist: asn1crypto (==0.23.0)
Requires-Dist: boto3 (==1.8.2)
Requires-Dist: botocore (==1.11.2)
Requires-Dist: cryptography (>=2.3)
Requires-Dist: Django (>=1.10.0)
Requires-Dist: djangorestframework (==3.6.4)
Requires-Dist: idna (==2.6)
Requires-Dist: PyJWT (==1.6.4)
Requires-Dist: python-dateutil (==2.6.1)
Requires-Dist: urllib3 (==1.22)
